acoular/__init__.py
acoular/base.py
acoular/calib.py
acoular/configuration.py
acoular/deprecation.py
acoular/environments.py
acoular/fastFuncs.py
acoular/fbeamform.py
acoular/fprocess.py
acoular/grids.py
acoular/h5cache.py
acoular/h5files.py
acoular/internal.py
acoular/microphones.py
acoular/process.py
acoular/sdinput.py
acoular/signals.py
acoular/sources.py
acoular/spectra.py
acoular/tbeamform.py
acoular/tfastfuncs.py
acoular/tprocess.py
acoular/traitsviews.py
acoular/trajectory.py
acoular/version.py
acoular/aiaa/__init__.py
acoular/aiaa/aiaa.py
acoular/demo/__init__.py
acoular/demo/acoular_demo.py
acoular/tools/__init__.py
acoular/tools/helpers.py
acoular/tools/metrics.py
acoular/tools/utils.py
acoular/xml/HW90D240_f10.xml
acoular/xml/W90_D105_f10.xml
acoular/xml/acousticam_2c.xml
acoular/xml/acousticam_4c.xml
acoular/xml/array38.xml
acoular/xml/array92x.xml
acoular/xml/array_56.xml
acoular/xml/array_56_10_9.xml
acoular/xml/array_56_bomb.xml
acoular/xml/array_56_v2.xml
acoular/xml/array_64.xml
acoular/xml/array_84_10_9.xml
acoular/xml/array_84_bomb_v3.xml
acoular/xml/calib_vw_ring32.xml
acoular/xml/gfai_ring32.xml
acoular/xml/minidsp_uma-16.xml
acoular/xml/minidsp_uma-16_mirrored.xml
acoular/xml/tub_vogel64.xml
acoular-25.10.dist-info/METADATA
acoular-25.10.dist-info/WHEEL
acoular-25.10.dist-info/licenses/AUTHORS.rst
acoular-25.10.dist-info/licenses/LICENSE
acoular-25.10.dist-info/RECORD
