Metadata-Version: 2.4
Name: acoular
Version: 25.10
Summary: Python library for acoustic beamforming
Project-URL: homepage, https://acoular.org
Project-URL: documentation, https://acoular.org
Project-URL: repository, https://github.com/acoular/acoular
Author-email: Acoular Development Team <info@acoular.org>
Maintainer-email: Adam Kujawski <adam.kujawski@tu-berlin.de>, Art Pelling <a.pelling@tu-berlin.de>, Ennes Sarradj <ennes.sarradj@tu-berlin.de>, Gert Herold <gert.herold@tu-berlin.de>, Mikolaj Czuchaj <mikolaj.czuchaj@tu-berlin.de>, Simon Jekosch <s.jekosch@tu-berlin.de>
License: BSD 3-Clause License
License-File: AUTHORS.rst
License-File: LICENSE
Keywords: acoustics,beamforming,microphone array
Classifier: Development Status :: 5 - Production/Stable
Classifier: Intended Audience :: Education
Classifier: Intended Audience :: Science/Research
Classifier: License :: OSI Approved :: BSD License
Classifier: Programming Language :: Python :: 3.10
Classifier: Programming Language :: Python :: 3.11
Classifier: Programming Language :: Python :: 3.12
Classifier: Programming Language :: Python :: 3.13
Classifier: Topic :: Scientific/Engineering :: Physics
Requires-Python: <3.14,>=3.10
Requires-Dist: numba
Requires-Dist: numpy
Requires-Dist: scikit-learn
Requires-Dist: scipy!=1.16.*,>=1.1.0
Requires-Dist: tables
Requires-Dist: traits>=6.0
Provides-Extra: dev
Requires-Dist: graphviz; extra == 'dev'
Requires-Dist: h5py; extra == 'dev'
Requires-Dist: hatch; extra == 'dev'
Requires-Dist: ipython; extra == 'dev'
Requires-Dist: matplotlib; extra == 'dev'
Requires-Dist: numpydoc; extra == 'dev'
Requires-Dist: pickleshare; extra == 'dev'
Requires-Dist: pydata-sphinx-theme; extra == 'dev'
Requires-Dist: pylops; extra == 'dev'
Requires-Dist: pytest; extra == 'dev'
Requires-Dist: pytest-cases; extra == 'dev'
Requires-Dist: pytest-cov; extra == 'dev'
Requires-Dist: pytest-env; extra == 'dev'
Requires-Dist: pytest-mock; extra == 'dev'
Requires-Dist: pytest-profiling; extra == 'dev'
Requires-Dist: pytest-regtest; extra == 'dev'
Requires-Dist: pyyaml; extra == 'dev'
Requires-Dist: ruff==0.8.1; extra == 'dev'
Requires-Dist: setuptools; extra == 'dev'
Requires-Dist: sounddevice; extra == 'dev'
Requires-Dist: sphinx; extra == 'dev'
Requires-Dist: sphinx-copybutton; extra == 'dev'
Requires-Dist: sphinx-gallery; extra == 'dev'
Requires-Dist: sphinxcontrib-bibtex; extra == 'dev'
Requires-Dist: traitsui; extra == 'dev'
Provides-Extra: docs
Requires-Dist: graphviz; extra == 'docs'
Requires-Dist: ipython; extra == 'docs'
Requires-Dist: matplotlib; extra == 'docs'
Requires-Dist: numpydoc; extra == 'docs'
Requires-Dist: pickleshare; extra == 'docs'
Requires-Dist: pydata-sphinx-theme; extra == 'docs'
Requires-Dist: setuptools; extra == 'docs'
Requires-Dist: sounddevice; extra == 'docs'
Requires-Dist: sphinx; extra == 'docs'
Requires-Dist: sphinx-copybutton; extra == 'docs'
Requires-Dist: sphinx-gallery; extra == 'docs'
Requires-Dist: sphinxcontrib-bibtex; extra == 'docs'
Provides-Extra: full
Requires-Dist: matplotlib; extra == 'full'
Requires-Dist: pylops; extra == 'full'
Requires-Dist: sounddevice; extra == 'full'
Provides-Extra: tests
Requires-Dist: h5py; extra == 'tests'
Requires-Dist: pylops; extra == 'tests'
Requires-Dist: pytest; extra == 'tests'
Requires-Dist: pytest-cases; extra == 'tests'
Requires-Dist: pytest-cov; extra == 'tests'
Requires-Dist: pytest-env; extra == 'tests'
Requires-Dist: pytest-mock; extra == 'tests'
Requires-Dist: pytest-profiling; extra == 'tests'
Requires-Dist: pytest-regtest; extra == 'tests'
Requires-Dist: pyyaml; extra == 'tests'
Requires-Dist: sounddevice; extra == 'tests'
Requires-Dist: traitsui; extra == 'tests'
